pysparse.so
pysap/__init__.py
pysap/configure.py
pysap/data.py
pysap/info.py
pysap/utils.py
pysap/apps/__init__.py
pysap/apps/pypipe_config.json
pysap/base/__init__.py
pysap/base/exceptions.py
pysap/base/image.py
pysap/base/io.py
pysap/base/observable.py
pysap/base/plugins.py
pysap/base/transform.py
pysap/base/utils.py
pysap/base/loaders/__init__.py
pysap/base/loaders/fits.py
pysap/base/loaders/loader_base.py
pysap/base/loaders/mat.py
pysap/base/loaders/nifti.py
pysap/base/loaders/numpy_binary.py
pysap/extensions/__init__.py
pysap/extensions/formating.py
pysap/extensions/sparse2d.py
pysap/extensions/tools.py
pysap/extensions/transform.py
pysap/extensions/wrapper.py
pysap/plotting/__init__.py
pysap/plotting/image.py
pysap/plotting/transform.py
pysap/plotting/utils.py
pysap/plugins/__init__.py
pysap/test/errors.json
pysap/test/test_binding.py
pysap/test/test_examples.py
python_pySAP-0.0.5.data/scripts/pysapview3
python_pySAP-0.0.5.dist-info/LICENSE
python_pySAP-0.0.5.dist-info/METADATA
python_pySAP-0.0.5.dist-info/WHEEL
python_pySAP-0.0.5.dist-info/top_level.txt
python_pySAP-0.0.5.dist-info/RECORD
