Metadata-Version: 2.1
Name: python-pySAP
Version: 0.0.5
Summary: 
Requires-Dist: scipy (==1.5.4)
Requires-Dist: numpy (==1.19.5)
Requires-Dist: matplotlib (==3.3.4)
Requires-Dist: astropy (==4.1)
Requires-Dist: nibabel (==3.2.1)
Requires-Dist: pyqtgraph (==0.11.1)
Requires-Dist: progressbar2 (==3.53.1)
Requires-Dist: modopt (==1.5.1)
Requires-Dist: scikit-learn (==0.24.1)
Requires-Dist: PyWavelets (==1.1.1)
Provides-Extra: gui
Requires-Dist: PySide (>=1.2.2) ; extra == 'gui'
